setuptools_markdown.py
setuptools_markdown-0.4.dist-info/LICENSE-MIT
setuptools_markdown-0.4.dist-info/METADATA
setuptools_markdown-0.4.dist-info/WHEEL
setuptools_markdown-0.4.dist-info/entry_points.txt
setuptools_markdown-0.4.dist-info/top_level.txt
setuptools_markdown-0.4.dist-info/RECORD
