Metadata-Version: 2.1
Name: setuptools-markdown
Version: 0.4
Summary: Use Markdown for your project description
Home-page: https://github.com/msabramo/setuptools-markdown
Author: Marc Abramowitz
Author-email: marc@marc-abramowitz.com
License: MIT
Keywords: distutils setuptools markdown
Platform: UNKNOWN
Requires-Dist: pypandoc
